LICENSE
MANIFEST.in
README.rst
setup.cfg
setup.py
django_image_moderation.egg-info/PKG-INFO
django_image_moderation.egg-info/SOURCES.txt
django_image_moderation.egg-info/dependency_links.txt
django_image_moderation.egg-info/top_level.txt
image_moderation/__init__.py
image_moderation/fields.py