Metadata-Version: 2.1
Name: django-image-moderation
Version: 0.1
Summary: Django automatic image moderation field using AWS Rekognition
Home-page: https://github.com/alexjmpb/django-image-moderation
Author: AlexJMPB
Author-email: alexjmpmendoza@gmail.com
Maintainer: AlexJMPB
Maintainer-email: alexjmpmendoza@gmail.com
License: MIT
Keywords: django ai moderation image rekognition aws
Platform: UNKNOWN
Classifier: Environment :: Web Environment
Classifier: Framework :: Django
Classifier: Intended Audience :: Developers
Classifier: License :: OSI Approved :: MIT License
Classifier: Operating System :: OS Independent
Classifier: Programming Language :: Python :: 3
Classifier: Topic :: Software Development :: Libraries :: Python Modules
Requires-Python: >=3.9
License-File: LICENSE
